waldur_site_agent_cscs_dwdi/__init__.py
waldur_site_agent_cscs_dwdi/backend.py
waldur_site_agent_cscs_dwdi/client.py
waldur_site_agent_cscs_dwdi-0.8.2.dist-info/METADATA
waldur_site_agent_cscs_dwdi-0.8.2.dist-info/WHEEL
waldur_site_agent_cscs_dwdi-0.8.2.dist-info/entry_points.txt
waldur_site_agent_cscs_dwdi-0.8.2.dist-info/RECORD
