Metadata-Version: 2.4
Name: waldur-site-agent-cscs-dwdi
Version: 0.8.2
Summary: CSCS-DWDI reporting plugin for Waldur Site Agent
Author-email: OpenNode Team <info@opennodecloud.com>
Requires-Python: <4,>=3.9
Requires-Dist: httpx>=0.25.0
Requires-Dist: waldur-site-agent>=0.7.0
